<?xml version="1.0" encoding="UTF-8" standalone="no" ?>
<!--Erstellt mit MOSES-Profil-ARC am: 09.03.2023, 17:24:26-->
<FRAME-DUMP VERSION="1.0" Baugruppe="10122">
    <SNaht Name="AutoDetect_4_0" ID="-308368301" ZRotLock="0" WkzWkl="45" WkzName="MRW510_CDD_10GH">
        <Kontur>
            <Punkt X="-14.9999999" Y="2.999999999999972" Z="-426">
                <Fl_Norm X="-1" Y="0" Z="0" />
                <Fl_Norm X="0" Y="1" Z="0" />
                <Rot X="90" Y="0" Z="0" />
                <Ext-Achswerte EA3="-90" />
            </Punkt>
            <Punkt X="-14.9999999" Y="2.999999999999972" Z="-386.0000000000004">
                <Fl_Norm X="-1" Y="0" Z="0" />
                <Fl_Norm X="0" Y="1" Z="0" />
                <Rot X="90" Y="0" Z="0" />
                <Ext-Achswerte EA3="-90" />
            </Punkt>
            <Punkt X="-14.9999999" Y="2.999999999999972" Z="-332.0000000000003">
                <Fl_Norm X="-1" Y="0" Z="0" />
                <Fl_Norm X="0" Y="1" Z="0" />
                <Rot X="90" Y="0" Z="0" />
                <Ext-Achswerte EA3="-90" />
            </Punkt>
        </Kontur>
        <Frames>
            <Frame>
                <Pos X="-14.99999990000002" Y="2.999999999999993" Z="-426.0000000000008" />
                <XVek X="-0.1227913466174791" Y="4.512800997260606e-16" Z="-0.9924325091389672" />
                <YVek X="-0.6990853645605903" Y="-0.7097873355780226" Z="0.0864961924609281" />
                <ZVek X="-0.7044160264027591" Y="0.7044160264027582" Z="0.08715574274765828" />
                <Rot X="90" Y="0" Z="0" />
                <Ext-Achswerte EA3="-90" />
            </Frame>
            <Frame>
                <Pos X="-14.99999990000001" Y="3" Z="-386.0000000000003" />
                <XVek X="0.2419547857523648" Y="-4.163336342344333e-17" Z="-0.970287525247814" />
                <YVek X="-0.6756735354111854" Y="-0.7176885430348757" Z="-0.1684886605722384" />
                <ZVek X="-0.6963642403200189" Y="0.6963642403200191" Z="-0.1736481776669302" />
                <Rot X="90" Y="0" Z="0" />
                <Ext-Achswerte EA3="-90" />
            </Frame>
            <Frame>
                <Pos X="-14.99999989999998" Y="2.999999999999929" Z="-332.0000000000003" />
                <XVek X="0.2419547857523648" Y="6.938893903907225e-17" Z="-0.970287525247814" />
                <YVek X="-0.6756735354111854" Y="-0.7176885430348757" Z="-0.1684886605722385" />
                <ZVek X="-0.6963642403200189" Y="0.6963642403200191" Z="-0.1736481776669301" />
                <Rot X="90" Y="0" Z="0" />
                <Ext-Achswerte EA3="-90" />
            </Frame>
        </Frames>
    </SNaht>
    <SNaht Name="AutoDetect_52_1" ID="-308368105" ZRotLock="0" WkzWkl="45" WkzName="MRW510_CDD_10GH">
        <Kontur>
            <Punkt X="-1490" Y="2.999999900000006" Z="-328">
                <Fl_Norm X="1" Y="0" Z="0" />
                <Fl_Norm X="0" Y="1" Z="0" />
                <Rot X="90" Y="0" Z="0" />
                <Ext-Achswerte EA3="-90" />
            </Punkt>
            <Punkt X="-1490" Y="2.999999900000006" Z="-368.0000000000004">
                <Fl_Norm X="1" Y="0" Z="0" />
                <Fl_Norm X="0" Y="1" Z="0" />
                <Rot X="90" Y="0" Z="0" />
                <Ext-Achswerte EA3="-90" />
            </Punkt>
            <Punkt X="-1490" Y="2.999999900000006" Z="-419.9999999999999">
                <Fl_Norm X="1" Y="0" Z="0" />
                <Fl_Norm X="0" Y="1" Z="0" />
                <Rot X="90" Y="0" Z="0" />
                <Ext-Achswerte EA3="-90" />
            </Punkt>
        </Kontur>
        <Frames>
            <Frame>
                <Pos X="-1490" Y="2.999999900000716" Z="-328.0000000000008" />
                <XVek X="0.07097044845508371" Y="-0.009343436794009438" Z="0.9974346573259627" />
                <YVek X="0.7042128511290755" Y="-0.7077183369378909" Z="-0.05673637163693453" />
                <ZVek X="0.7064329095892564" Y="0.7064329095892562" Z="-0.04364731948831446" />
                <Rot X="90" Y="0" Z="0" />
                <Ext-Achswerte EA3="-90" />
            </Frame>
            <Frame>
                <Pos X="-1490.000000000001" Y="2.999999899999125" Z="-368.0000000000004" />
                <XVek X="-0.2758330642013614" Y="0.03631411181929373" Z="0.9605193418021646" />
                <YVek X="0.6625654424257353" Y="-0.7167692307056008" Z="0.2173681310976627" />
                <ZVek X="0.6963642403200191" Y="0.6963642403200189" Z="0.1736481776669305" />
                <Rot X="90" Y="0" Z="0" />
                <Ext-Achswerte EA3="-90" />
            </Frame>
            <Frame>
                <Pos X="-1490.000000000002" Y="2.999999899999807" Z="-420.0000000000007" />
                <XVek X="-0.2758330642013614" Y="0.03631411181929373" Z="0.9605193418021646" />
                <YVek X="0.6625654424257353" Y="-0.7167692307056008" Z="0.2173681310976627" />
                <ZVek X="0.6963642403200191" Y="0.6963642403200189" Z="0.1736481776669305" />
                <Rot X="90" Y="0" Z="0" />
                <Ext-Achswerte EA3="-90" />
            </Frame>
        </Frames>
    </SNaht>
    <SNaht Name="AutoDetect_51_2" ID="-308368023" ZRotLock="0" WkzWkl="45" WkzName="MRW510_CDD_10GH">
        <Kontur>
            <Punkt X="-1500" Y="2.999999900000006" Z="-328">
                <Fl_Norm X="-1" Y="0" Z="0" />
                <Fl_Norm X="0" Y="1" Z="0" />
                <Rot X="90" Y="0" Z="0" />
                <Ext-Achswerte EA3="-90" />
            </Punkt>
            <Punkt X="-1500" Y="2.999999900000006" Z="-368.0000000000004">
                <Fl_Norm X="-1" Y="0" Z="0" />
                <Fl_Norm X="0" Y="1" Z="0" />
                <Rot X="90" Y="0" Z="0" />
                <Ext-Achswerte EA3="-90" />
            </Punkt>
            <Punkt X="-1500" Y="2.999999900000006" Z="-419.9999999999999">
                <Fl_Norm X="-1" Y="0" Z="0" />
                <Fl_Norm X="0" Y="1" Z="0" />
                <Rot X="90" Y="0" Z="0" />
                <Ext-Achswerte EA3="-90" />
            </Punkt>
        </Kontur>
        <Frames>
            <Frame>
                <Pos X="-1500" Y="2.999999899999921" Z="-328.0000000000003" />
                <XVek X="0.281302219524468" Y="0.2236736229127897" Z="-0.9331876401365778" />
                <YVek X="-0.6494772154212799" Y="-0.6715070382906189" Z="-0.3567318939691009" />
                <ZVek X="-0.7064335835301352" Y="0.7064335835301352" Z="-0.04362549852486493" />
                <Rot X="90" Y="0" Z="0" />
                <Ext-Achswerte EA3="-90" />
            </Frame>
            <Frame>
                <Pos X="-1500" Y="2.999999900000262" Z="-368.0000000000006" />
                <XVek X="-0.1633251363530677" Y="0.08184251295467548" Z="-0.9831717565657161" />
                <YVek X="-0.698857456595245" Y="-0.7130067656598966" Z="0.05674158514210356" />
                <ZVek X="-0.696364240320019" Y="0.696364240320019" Z="0.1736481776669302" />
                <Rot X="90" Y="0" Z="0" />
                <Ext-Achswerte EA3="-90" />
            </Frame>
            <Frame>
                <Pos X="-1500.000000000001" Y="2.999999900001171" Z="-420.0000000000008" />
                <XVek X="-0.2419547857523648" Y="3.519794442636283e-16" Z="-0.970287525247814" />
                <YVek X="-0.6756735354111855" Y="-0.7176885430348755" Z="0.1684886605722382" />
                <ZVek X="-0.6963642403200186" Y="0.6963642403200192" Z="0.1736481776669304" />
                <Rot X="90" Y="0" Z="0" />
                <Ext-Achswerte EA3="-90" />
            </Frame>
        </Frames>
    </SNaht>
    <SNaht Name="AutoDetect_3_3" ID="-308367959" ZRotLock="0" WkzWkl="45" WkzName="MRW510_CDD_10GH">
        <Kontur>
            <Punkt X="-14.9999999" Y="-3.000000000000028" Z="-322">
                <Fl_Norm X="-1" Y="0" Z="0" />
                <Fl_Norm X="0" Y="-1" Z="0" />
                <Rot X="-90" Y="0" Z="-0" />
                <Ext-Achswerte EA3="90" />
            </Punkt>
            <Punkt X="-14.9999999" Y="-3.000000000000028" Z="-362.0000000000002">
                <Fl_Norm X="-1" Y="0" Z="0" />
                <Fl_Norm X="0" Y="-1" Z="0" />
                <Rot X="-90" Y="0" Z="-0" />
                <Ext-Achswerte EA3="90" />
            </Punkt>
            <Punkt X="-14.9999999" Y="-3.000000000000028" Z="-416.0000000000003">
                <Fl_Norm X="-1" Y="0" Z="0" />
                <Fl_Norm X="0" Y="-1" Z="0" />
                <Rot X="-90" Y="0" Z="-0" />
                <Ext-Achswerte EA3="90" />
            </Punkt>
        </Kontur>
        <Frames>
            <Frame>
                <Pos X="-14.99999990000003" Y="-3.000000000000071" Z="-321.9999999999997" />
                <XVek X="-0.1410372715625492" Y="0.01856790905412185" Z="0.9898301474412413" />
                <YVek X="-0.6956339193693329" Y="0.7095444274323534" Z="-0.11242844712329" />
                <ZVek X="-0.7044160264027589" Y="-0.7044160264027586" Z="-0.08715574274765821" />
                <Rot X="-90" Y="0" Z="-0" />
                <Ext-Achswerte EA3="90" />
            </Frame>
            <Frame>
                <Pos X="-14.99999990000006" Y="-3.000000000000057" Z="-362.0000000000003" />
                <XVek X="0.2758330642013614" Y="-0.03631411181929374" Z="0.9605193418021646" />
                <YVek X="-0.6625654424257355" Y="0.7167692307056008" Z="0.2173681310976628" />
                <ZVek X="-0.696364240320019" Y="-0.696364240320019" Z="0.1736481776669304" />
                <Rot X="-90" Y="0" Z="-0" />
                <Ext-Achswerte EA3="90" />
            </Frame>
            <Frame>
                <Pos X="-14.99999990000007" Y="-3.000000000000092" Z="-416.0000000000007" />
                <XVek X="0.2758330642013614" Y="-0.0363141118192937" Z="0.9605193418021646" />
                <YVek X="-0.6625654424257355" Y="0.7167692307056007" Z="0.2173681310976627" />
                <ZVek X="-0.696364240320019" Y="-0.6963642403200189" Z="0.1736481776669305" />
                <Rot X="-90" Y="0" Z="-0" />
                <Ext-Achswerte EA3="90" />
            </Frame>
        </Frames>
    </SNaht>
    <SNaht Name="AutoDetect_35_4" ID="-308367849" ZRotLock="0" WkzWkl="45" WkzName="MRW510_CDD_10GH">
        <Kontur>
            <Punkt X="-1490" Y="-2.999999900000006" Z="-328">
                <Fl_Norm X="1" Y="0" Z="0" />
                <Fl_Norm X="0" Y="-1" Z="0" />
                <Rot X="-90" Y="0" Z="-0" />
                <Ext-Achswerte EA3="90" />
            </Punkt>
            <Punkt X="-1490" Y="-2.999999900000006" Z="-368.0000000000003">
                <Fl_Norm X="1" Y="0" Z="0" />
                <Fl_Norm X="0" Y="-1" Z="0" />
                <Rot X="-90" Y="0" Z="-0" />
                <Ext-Achswerte EA3="90" />
            </Punkt>
            <Punkt X="-1490" Y="-2.999999900000006" Z="-419.9999999999999">
                <Fl_Norm X="1" Y="0" Z="0" />
                <Fl_Norm X="0" Y="-1" Z="0" />
                <Rot X="-90" Y="0" Z="-0" />
                <Ext-Achswerte EA3="90" />
            </Punkt>
        </Kontur>
        <Frames>
            <Frame>
                <Pos X="-1490" Y="-2.999999900000034" Z="-328.0000000000005" />
                <XVek X="-0.2813342948401902" Y="-0.2236827103902355" Z="-0.9331757924524462" />
                <YVek X="0.6494639240344724" Y="0.6715045935419656" Z="-0.356760693224162" />
                <ZVek X="0.7064330300350614" Y="-0.7064330300350611" Z="-0.04364342047736868" />
                <Rot X="-90" Y="0" Z="-0" />
                <Ext-Achswerte EA3="90" />
            </Frame>
            <Frame>
                <Pos X="-1490.000000000002" Y="-2.999999900000262" Z="-368.0000000000003" />
                <XVek X="0.1633251363530679" Y="-0.08184251295467551" Z="-0.983171756565716" />
                <YVek X="0.6988574565952448" Y="0.7130067656598967" Z="0.05674158514210364" />
                <ZVek X="0.696364240320019" Y="-0.6963642403200188" Z="0.1736481776669304" />
                <Rot X="-90" Y="0" Z="-0" />
                <Ext-Achswerte EA3="90" />
            </Frame>
            <Frame>
                <Pos X="-1490.000000000001" Y="-2.999999900000148" Z="-420.0000000000004" />
                <XVek X="0.2419547857523648" Y="-2.914335439641036e-16" Z="-0.970287525247814" />
                <YVek X="0.6756735354111852" Y="0.7176885430348759" Z="0.1684886605722382" />
                <ZVek X="0.696364240320019" Y="-0.696364240320019" Z="0.1736481776669304" />
                <Rot X="-90" Y="0" Z="-0" />
                <Ext-Achswerte EA3="90" />
            </Frame>
        </Frames>
    </SNaht>
    <SNaht Name="AutoDetect_36_5" ID="-308367788" ZRotLock="0" WkzWkl="45" WkzName="MRW510_CDD_10GH">
        <Kontur>
            <Punkt X="-1500" Y="-2.999999900000006" Z="-328">
                <Fl_Norm X="-1" Y="0" Z="0" />
                <Fl_Norm X="0" Y="-1" Z="0" />
                <Rot X="-90" Y="0" Z="-0" />
                <Ext-Achswerte EA3="90" />
            </Punkt>
            <Punkt X="-1500" Y="-2.999999900000006" Z="-368.0000000000004">
                <Fl_Norm X="-1" Y="0" Z="0" />
                <Fl_Norm X="0" Y="-1" Z="0" />
                <Rot X="-90" Y="0" Z="-0" />
                <Ext-Achswerte EA3="90" />
            </Punkt>
            <Punkt X="-1500" Y="-2.999999900000006" Z="-419.9999999999999">
                <Fl_Norm X="-1" Y="0" Z="0" />
                <Fl_Norm X="0" Y="-1" Z="0" />
                <Rot X="-90" Y="0" Z="-0" />
                <Ext-Achswerte EA3="90" />
            </Punkt>
        </Kontur>
        <Frames>
            <Frame>
                <Pos X="-1500" Y="-2.999999900000262" Z="-328.0000000000006" />
                <XVek X="-0.07091634660496314" Y="0.009336314150316773" Z="0.9974385720545859" />
                <YVek X="-0.7042172673395044" Y="0.7077174019854249" Z="-0.05669320336584657" />
                <ZVek X="-0.7064339404113349" Y="-0.706433940411336" Z="-0.04361393893960321" />
                <Rot X="-90" Y="0" Z="-0" />
                <Ext-Achswerte EA3="90" />
            </Frame>
            <Frame>
                <Pos X="-1500" Y="-2.999999900000034" Z="-368.0000000000004" />
                <XVek X="0.2758330642013614" Y="-0.03631411181929374" Z="0.9605193418021646" />
                <YVek X="-0.6625654424257355" Y="0.7167692307056008" Z="0.2173681310976628" />
                <ZVek X="-0.696364240320019" Y="-0.696364240320019" Z="0.1736481776669304" />
                <Rot X="-90" Y="0" Z="-0" />
                <Ext-Achswerte EA3="90" />
            </Frame>
            <Frame>
                <Pos X="-1500.000000000001" Y="-2.999999900000716" Z="-420.0000000000011" />
                <XVek X="0.2758330642013614" Y="-0.0363141118192937" Z="0.9605193418021646" />
                <YVek X="-0.6625654424257355" Y="0.7167692307056007" Z="0.2173681310976627" />
                <ZVek X="-0.696364240320019" Y="-0.6963642403200189" Z="0.1736481776669305" />
                <Rot X="-90" Y="0" Z="-0" />
                <Ext-Achswerte EA3="90" />
            </Frame>
        </Frames>
    </SNaht>
    <SNaht Name="AutoDetect_3_6" ID="-308367730" ZRotLock="0" WkzWkl="45" WkzName="MRW510_CDD_10GH">
        <Kontur>
            <Punkt X="-14.9999999" Y="-73.90000000000003" Z="-307">
                <Fl_Norm X="-1" Y="0" Z="0" />
                <Fl_Norm X="0" Y="0" Z="-1" />
                <Rot X="180" Y="0" Z="0" />
                <Ext-Achswerte EA3="180" />
            </Punkt>
            <Punkt X="-14.9999999" Y="-27.99999999999999" Z="-307">
                <Fl_Norm X="-1" Y="0" Z="0" />
                <Fl_Norm X="0" Y="0" Z="-1" />
                <Rot X="180" Y="0" Z="0" />
                <Ext-Achswerte EA3="180" />
            </Punkt>
        </Kontur>
        <Frames>
            <Frame>
                <Pos X="-14.99999989999986" Y="-73.90000000000008" Z="-307.0000000000003" />
                <XVek X="-0.6309120413685945" Y="-0.3143786283125726" Z="0.7093067560064674" />
                <YVek X="-0.3420918602650993" Y="0.9332804446966944" Z="0.1093653084259548" />
                <ZVek X="-0.6963642403200186" Y="-0.1736481776669302" Z="-0.6963642403200192" />
                <Rot X="180" Y="0" Z="0" />
                <Ext-Achswerte EA3="180" />
            </Frame>
            <Frame>
                <Pos X="-14.99999989999975" Y="-28" Z="-307.0000000000005" />
                <XVek X="-0.4726981844248816" Y="-0.3696039428423756" Z="0.7999683442966919" />
                <YVek X="-0.3456047964522455" Y="0.9128193883941798" Z="0.21752721402362" />
                <ZVek X="-0.8106255307542581" Y="-0.1736481776669302" Z="-0.5592249630357462" />
                <Rot X="180" Y="0" Z="0" />
                <Ext-Achswerte EA3="180" />
            </Frame>
        </Frames>
    </SNaht>
    <SNaht Name="AutoDetect_1_7" ID="-308367666" ZRotLock="0" WkzWkl="45" WkzName="MRW510_CDD_10GH">
        <Kontur>
            <Punkt X="-15" Y="73.99999999999997" Z="-445">
                <Fl_Norm X="0" Y="0" Z="-1" />
                <Fl_Norm X="1" Y="-0" Z="-0" />
                <Rot X="180" Y="0" Z="0" />
                <Ext-Achswerte EA3="180" />
            </Punkt>
            <Punkt X="-15" Y="-74.00000000000003" Z="-445">
                <Fl_Norm X="0" Y="0" Z="-1" />
                <Fl_Norm X="1" Y="-0" Z="-0" />
                <Rot X="180" Y="0" Z="0" />
                <Ext-Achswerte EA3="180" />
            </Punkt>
        </Kontur>
        <Frames>
            <Frame>
                <Pos X="-15.00000000000011" Y="73.99999999999994" Z="-445" />
                <XVek X="-0.4396812331573745" Y="0.8701041940907696" Z="-0.2227085643500561" />
                <YVek X="0.5672365097670754" Y="0.461264568136993" Z="0.6822592910094077" />
                <ZVek X="0.6963642403200189" Y="0.1736481776669304" Z="-0.696364240320019" />
                <Rot X="180" Y="0" Z="0" />
                <Ext-Achswerte EA3="180" />
            </Frame>
            <Frame>
                <Pos X="-15.0000000000002" Y="-74.0000000000001" Z="-445.0000000000001" />
                <XVek X="-0.4396812331573745" Y="0.8701041940907696" Z="-0.2227085643500561" />
                <YVek X="0.5672365097670754" Y="0.461264568136993" Z="0.6822592910094077" />
                <ZVek X="0.6963642403200189" Y="0.1736481776669304" Z="-0.696364240320019" />
                <Rot X="180" Y="0" Z="0" />
                <Ext-Achswerte EA3="180" />
            </Frame>
        </Frames>
    </SNaht>
    <SNaht Name="AutoDetect_4_8" ID="-308367621" ZRotLock="0" WkzWkl="45" WkzName="MRW510_CDD_10GH">
        <Kontur>
            <Punkt X="-14.9999999" Y="73.89999999999999" Z="-307">
                <Fl_Norm X="-1" Y="0" Z="0" />
                <Fl_Norm X="0" Y="0" Z="-1" />
                <Rot X="180" Y="0" Z="0" />
                <Ext-Achswerte EA3="180" />
            </Punkt>
            <Punkt X="-14.9999999" Y="27.99999999999993" Z="-307">
                <Fl_Norm X="-1" Y="0" Z="0" />
                <Fl_Norm X="0" Y="0" Z="-1" />
                <Rot X="180" Y="0" Z="0" />
                <Ext-Achswerte EA3="180" />
            </Punkt>
        </Kontur>
        <Frames>
            <Frame>
                <Pos X="-14.99999989999986" Y="73.90000000000003" Z="-307.0000000000001" />
                <XVek X="0.6346155553801685" Y="-0.3041531218414728" Z="-0.7104603967453826" />
                <YVek X="-0.3351715108314596" Y="-0.9366627935746356" Z="0.101601522921246" />
                <ZVek X="-0.6963642403200189" Y="0.1736481776669306" Z="-0.6963642403200189" />
                <Rot X="180" Y="0" Z="0" />
                <Ext-Achswerte EA3="180" />
            </Frame>
            <Frame>
                <Pos X="-14.99999989999989" Y="27.99999999999995" Z="-307.0000000000004" />
                <XVek X="0.5660643242938792" Y="-0.3483900442521495" Z="-0.7471248609353722" />
                <YVek X="-0.4176727917102168" Y="-0.902576701875102" Z="0.104425745375635" />
                <ZVek X="-0.7107183829244238" Y="0.2529420374280409" Z="-0.656429513257169" />
                <Rot X="180" Y="0" Z="0" />
                <Ext-Achswerte EA3="180" />
            </Frame>
        </Frames>
    </SNaht>
    <SNaht Name="AutoDetect_37_9" ID="-308367558" ZRotLock="0" WkzWkl="45" WkzName="MRW510_CDD_10GH">
        <Kontur>
            <Punkt X="-1490" Y="-73.89999999999988" Z="-308">
                <Fl_Norm X="1" Y="0" Z="0" />
                <Fl_Norm X="0" Y="0" Z="-1" />
                <Rot X="180" Y="0" Z="0" />
                <Ext-Achswerte EA3="180" />
            </Punkt>
            <Punkt X="-1490" Y="-22.9999999" Z="-308">
                <Fl_Norm X="1" Y="0" Z="0" />
                <Fl_Norm X="0" Y="0" Z="-1" />
                <Rot X="180" Y="0" Z="0" />
                <Ext-Achswerte EA3="180" />
            </Punkt>
        </Kontur>
        <Frames>
            <Frame>
                <Pos X="-1490.000000000003" Y="-73.89999999999972" Z="-308.000000000001" />
                <XVek X="-0.6346155553801688" Y="0.3041531218414723" Z="-0.7104603967453826" />
                <YVek X="0.3351715108314589" Y="0.9366627935746358" Z="0.101601522921246" />
                <ZVek X="0.696364240320019" Y="-0.1736481776669301" Z="-0.6963642403200189" />
                <Rot X="180" Y="0" Z="0" />
                <Ext-Achswerte EA3="180" />
            </Frame>
            <Frame>
                <Pos X="-1490.000000000002" Y="-22.99999990000018" Z="-308.0000000000014" />
                <XVek X="-0.6734466693769873" Y="0.1291860736071061" Z="-0.7278602488740693" />
                <YVek X="0.2953113449255771" Y="0.9496486426634634" Z="-0.1046836426844639" />
                <ZVek X="0.6776878286226554" Y="-0.2854442395169695" Z="-0.6776878286226552" />
                <Rot X="180" Y="0" Z="0" />
                <Ext-Achswerte EA3="180" />
            </Frame>
        </Frames>
    </SNaht>
    <SNaht Name="AutoDetect_39_10" ID="-308367515" ZRotLock="0" WkzWkl="45" WkzName="MRW510_CDD_10GH">
        <Kontur>
            <Punkt X="-1500" Y="-73.90000000000015" Z="-308">
                <Fl_Norm X="-1" Y="0" Z="0" />
                <Fl_Norm X="0" Y="0" Z="-1" />
                <Rot X="180" Y="0" Z="0" />
                <Ext-Achswerte EA3="180" />
            </Punkt>
            <Punkt X="-1500" Y="-22.99999990000001" Z="-308">
                <Fl_Norm X="-1" Y="0" Z="0" />
                <Fl_Norm X="0" Y="0" Z="-1" />
                <Rot X="180" Y="0" Z="0" />
                <Ext-Achswerte EA3="180" />
            </Punkt>
        </Kontur>
        <Frames>
            <Frame>
                <Pos X="-1500" Y="-73.90000000000015" Z="-308.0000000000006" />
                <XVek X="-0.6309120413685939" Y="-0.3143786283125731" Z="0.7093067560064676" />
                <YVek X="-0.3420918602650995" Y="0.9332804446966942" Z="0.1093653084259554" />
                <ZVek X="-0.6963642403200191" Y="-0.1736481776669301" Z="-0.6963642403200189" />
                <Rot X="180" Y="0" Z="0" />
                <Ext-Achswerte EA3="180" />
            </Frame>
            <Frame>
                <Pos X="-1500.000000000002" Y="-22.99999990000018" Z="-308.0000000000003" />
                <XVek X="-0.6376028314936261" Y="0.006595559129886587" Z="0.77033702226433" />
                <YVek X="-0.1296318936522829" Y="0.9847856665248119" Z="-0.1157271063986526" />
                <ZVek X="-0.7593801428925" Y="-0.173648177666931" Z="-0.6270471345708551" />
                <Rot X="180" Y="0" Z="0" />
                <Ext-Achswerte EA3="180" />
            </Frame>
        </Frames>
    </SNaht>
    <SNaht Name="AutoDetect_55_11" ID="-308367477" ZRotLock="0" WkzWkl="45" WkzName="MRW510_CDD_10GH">
        <Kontur>
            <Punkt X="-1490" Y="73.89999999999972" Z="-308">
                <Fl_Norm X="1" Y="0" Z="0" />
                <Fl_Norm X="0" Y="0" Z="-1" />
                <Rot X="180" Y="0" Z="0" />
                <Ext-Achswerte EA3="180" />
            </Punkt>
            <Punkt X="-1490" Y="22.99999990000002" Z="-308">
                <Fl_Norm X="1" Y="0" Z="0" />
                <Fl_Norm X="0" Y="0" Z="-1" />
                <Rot X="180" Y="0" Z="0" />
                <Ext-Achswerte EA3="180" />
            </Punkt>
        </Kontur>
        <Frames>
            <Frame>
                <Pos X="-1490.000000000002" Y="73.89999999999972" Z="-308.0000000000007" />
                <XVek X="0.630912041368594" Y="0.3143786283125727" Z="0.7093067560064678" />
                <YVek X="0.342091860265099" Y="-0.9332804446966944" Z="0.1093653084259554" />
                <ZVek X="0.6963642403200193" Y="0.1736481776669298" Z="-0.6963642403200188" />
                <Rot X="180" Y="0" Z="0" />
                <Ext-Achswerte EA3="180" />
            </Frame>
            <Frame>
                <Pos X="-1490.000000000002" Y="22.99999989999984" Z="-308.0000000000008" />
                <XVek X="0.6376028314906623" Y="-0.006595559129886464" Z="0.7703370222667831" />
                <YVek X="0.1296318936527278" Y="-0.984785666524812" Z="-0.1157271063981535" />
                <ZVek X="0.7593801428949127" Y="0.1736481776669305" Z="-0.6270471345679336" />
                <Rot X="180" Y="0" Z="0" />
                <Ext-Achswerte EA3="180" />
            </Frame>
        </Frames>
    </SNaht>
    <SNaht Name="AutoDetect_56_12" ID="-308367430" ZRotLock="0" WkzWkl="45" WkzName="MRW510_CDD_10GH">
        <Kontur>
            <Punkt X="-1500" Y="73.89999999999988" Z="-308">
                <Fl_Norm X="-1" Y="0" Z="0" />
                <Fl_Norm X="0" Y="0" Z="-1" />
                <Rot X="180" Y="0" Z="0" />
                <Ext-Achswerte EA3="180" />
            </Punkt>
            <Punkt X="-1500" Y="22.99999990000001" Z="-308">
                <Fl_Norm X="-1" Y="0" Z="0" />
                <Fl_Norm X="0" Y="0" Z="-1" />
                <Rot X="180" Y="0" Z="0" />
                <Ext-Achswerte EA3="180" />
            </Punkt>
        </Kontur>
        <Frames>
            <Frame>
                <Pos X="-1500" Y="73.89999999999975" Z="-307.9999999999985" />
                <XVek X="0.6346155553801685" Y="-0.3041531218414728" Z="-0.7104603967453826" />
                <YVek X="-0.3351715108314596" Y="-0.9366627935746356" Z="0.101601522921246" />
                <ZVek X="-0.6963642403200189" Y="0.1736481776669306" Z="-0.6963642403200189" />
                <Rot X="180" Y="0" Z="0" />
                <Ext-Achswerte EA3="180" />
            </Frame>
            <Frame>
                <Pos X="-1500.000000000001" Y="22.99999990000015" Z="-308.0000000000006" />
                <XVek X="0.6734466691043786" Y="-0.1291860737209033" Z="-0.7278602491061007" />
                <YVek X="-0.2953113466107932" Y="-0.9496486419865262" Z="-0.1046836440713953" />
                <ZVek X="-0.677687828159203" Y="0.2854442417175794" Z="-0.6776878281592038" />
                <Rot X="180" Y="0" Z="0" />
                <Ext-Achswerte EA3="180" />
            </Frame>
        </Frames>
    </SNaht>
    <SNaht Name="AutoDetect_3_13" ID="-308367390" ZRotLock="0" WkzWkl="45" WkzName="MRW510_CDD_10GH">
        <Kontur>
            <Punkt X="-14.9999999" Y="-73.9000000000002" Z="-441">
                <Fl_Norm X="-1" Y="0" Z="0" />
                <Fl_Norm X="0" Y="0" Z="1" />
                <Rot X="0" Y="0" Z="0" />
                <Ext-Achswerte EA3="0" />
            </Punkt>
            <Punkt X="-14.9999999" Y="-28.00000000000004" Z="-441">
                <Fl_Norm X="-1" Y="0" Z="0" />
                <Fl_Norm X="0" Y="0" Z="1" />
                <Rot X="0" Y="0" Z="0" />
                <Ext-Achswerte EA3="0" />
            </Punkt>
        </Kontur>
        <Frames>
            <Frame>
                <Pos X="-14.99999990000015" Y="-73.90000000000022" Z="-441.0000000000006" />
                <XVek X="0.6694801722986665" Y="0.192444210581723" Z="0.7174688318753123" />
                <YVek X="-0.2585984216936965" Y="0.9658216896542197" Z="-0.01775725460192135" />
                <ZVek X="-0.6963642403200189" Y="-0.1736481776669302" Z="0.6963642403200191" />
                <Rot X="0" Y="0" Z="0" />
                <Ext-Achswerte EA3="0" />
            </Frame>
            <Frame>
                <Pos X="-14.99999990000012" Y="-28.00000000000001" Z="-441.000000000001" />
                <XVek X="0.6327352894682909" Y="0.189774243637337" Z="0.7507541474499856" />
                <YVek X="-0.3043742320490064" Y="0.9524218997735442" Z="0.01577503395656679" />
                <ZVek X="-0.7120409962397221" Y="-0.2384916377645763" Z="0.6603933361189485" />
                <Rot X="0" Y="0" Z="0" />
                <Ext-Achswerte EA3="0" />
            </Frame>
        </Frames>
    </SNaht>
    <SNaht Name="AutoDetect_2_14" ID="-308367330" ZRotLock="0" WkzWkl="45" WkzName="MRW510_CDD_10GH">
        <Kontur>
            <Punkt X="-15" Y="74.00000000000003" Z="-303">
                <Fl_Norm X="0" Y="0" Z="1" />
                <Fl_Norm X="1" Y="-0" Z="-0" />
                <Rot X="0" Y="0" Z="0" />
                <Ext-Achswerte EA3="0" />
            </Punkt>
            <Punkt X="-15" Y="-74.00000000000006" Z="-303">
                <Fl_Norm X="0" Y="0" Z="1" />
                <Fl_Norm X="1" Y="-0" Z="-0" />
                <Rot X="0" Y="0" Z="0" />
                <Ext-Achswerte EA3="0" />
            </Punkt>
        </Kontur>
        <Frames>
            <Frame>
                <Pos X="-15.00000000000006" Y="74.00000000000004" Z="-303.0000000000003" />
                <XVek X="0.2419547857523648" Y="-0.970287525247814" Z="8.789149770123881e-17" />
                <YVek X="0.6756735354111852" Y="0.1684886605722384" Z="-0.7176885430348758" />
                <ZVek X="0.696364240320019" Y="0.1736481776669302" Z="0.696364240320019" />
                <Rot X="0" Y="0" Z="0" />
                <Ext-Achswerte EA3="0" />
            </Frame>
            <Frame>
                <Pos X="-15.00000000000009" Y="-74.00000000000009" Z="-303.0000000000005" />
                <XVek X="0.2419547857523648" Y="-0.970287525247814" Z="8.789149770123881e-17" />
                <YVek X="0.6756735354111852" Y="0.1684886605722384" Z="-0.7176885430348758" />
                <ZVek X="0.696364240320019" Y="0.1736481776669302" Z="0.696364240320019" />
                <Rot X="0" Y="0" Z="0" />
                <Ext-Achswerte EA3="0" />
            </Frame>
        </Frames>
    </SNaht>
    <SNaht Name="AutoDetect_4_15" ID="-308367285" ZRotLock="0" WkzWkl="45" WkzName="MRW510_CDD_10GH">
        <Kontur>
            <Punkt X="-14.9999999" Y="73.90000000000008" Z="-440.9999999999998">
                <Fl_Norm X="-1" Y="0" Z="0" />
                <Fl_Norm X="0" Y="0" Z="1" />
                <Rot X="0" Y="0" Z="0" />
                <Ext-Achswerte EA3="0" />
            </Punkt>
            <Punkt X="-14.9999999" Y="27.99999999999996" Z="-441">
                <Fl_Norm X="-1" Y="0" Z="0" />
                <Fl_Norm X="0" Y="0" Z="1" />
                <Rot X="0" Y="0" Z="0" />
                <Ext-Achswerte EA3="0" />
            </Punkt>
        </Kontur>
        <Frames>
            <Frame>
                <Pos X="-14.9999999000002" Y="73.90000000000015" Z="-441.0000000000003" />
                <XVek X="-0.6346155553801681" Y="0.3041531218414738" Z="-0.7104603967453825" />
                <YVek X="-0.3351715108314601" Y="-0.9366627935746352" Z="-0.1016015229212469" />
                <ZVek X="-0.696364240320019" Y="0.1736481776669304" Z="0.6963642403200189" />
                <Rot X="0" Y="0" Z="0" />
                <Ext-Achswerte EA3="0" />
            </Frame>
            <Frame>
                <Pos X="-14.99999990000026" Y="27.99999999999999" Z="-441.0000000000003" />
                <XVek X="-0.4817414509979709" Y="0.3556452007451368" Z="-0.8009005341347456" />
                <YVek X="-0.3393348320540659" Y="-0.918347865234033" Z="-0.2036886599075496" />
                <ZVek X="-0.8079461901297688" Y="0.1736481776669304" Z="0.5630890375844176" />
                <Rot X="0" Y="0" Z="0" />
                <Ext-Achswerte EA3="0" />
            </Frame>
        </Frames>
    </SNaht>
    <SNaht Name="AutoDetect_40_16" ID="-308367220" ZRotLock="0" WkzWkl="45" WkzName="MRW510_CDD_10GH">
        <Kontur>
            <Punkt X="-1490" Y="-73.89999999999982" Z="-440">
                <Fl_Norm X="1" Y="0" Z="0" />
                <Fl_Norm X="0" Y="0" Z="1" />
                <Rot X="0" Y="0" Z="0" />
                <Ext-Achswerte EA3="0" />
            </Punkt>
            <Punkt X="-1490" Y="-22.99999990000001" Z="-440">
                <Fl_Norm X="1" Y="0" Z="0" />
                <Fl_Norm X="0" Y="0" Z="1" />
                <Rot X="0" Y="0" Z="0" />
                <Ext-Achswerte EA3="0" />
            </Punkt>
        </Kontur>
        <Frames>
            <Frame>
                <Pos X="-1490.000000000002" Y="-73.89999999999964" Z="-439.9999999999993" />
                <XVek X="0.6346155553801681" Y="-0.3041531218414738" Z="-0.7104603967453825" />
                <YVek X="0.3351715108314601" Y="0.9366627935746353" Z="-0.101601522921247" />
                <ZVek X="0.696364240320019" Y="-0.1736481776669304" Z="0.6963642403200189" />
                <Rot X="0" Y="0" Z="0" />
                <Ext-Achswerte EA3="0" />
            </Frame>
            <Frame>
                <Pos X="-1490.000000000001" Y="-22.99999989999984" Z="-440.0000000000001" />
                <XVek X="0.6391250575876232" Y="0.01736515052514442" Z="-0.7689067643809986" />
                <YVek X="0.1226280444090503" Y="0.9846546409478774" Z="0.1241676317895236" />
                <ZVek X="0.7592638036203421" Y="-0.1736481776669304" Z="0.6271879996499652" />
                <Rot X="0" Y="0" Z="0" />
                <Ext-Achswerte EA3="0" />
            </Frame>
        </Frames>
    </SNaht>
    <SNaht Name="AutoDetect_38_17" ID="-308367176" ZRotLock="0" WkzWkl="45" WkzName="MRW510_CDD_10GH">
        <Kontur>
            <Punkt X="-1500" Y="-73.90000000000003" Z="-440">
                <Fl_Norm X="-1" Y="0" Z="0" />
                <Fl_Norm X="0" Y="0" Z="1" />
                <Rot X="0" Y="0" Z="0" />
                <Ext-Achswerte EA3="0" />
            </Punkt>
            <Punkt X="-1500" Y="-22.99999990000001" Z="-440">
                <Fl_Norm X="-1" Y="0" Z="0" />
                <Fl_Norm X="0" Y="0" Z="1" />
                <Rot X="0" Y="0" Z="0" />
                <Ext-Achswerte EA3="0" />
            </Punkt>
        </Kontur>
        <Frames>
            <Frame>
                <Pos X="-1500" Y="-73.89999999999995" Z="-440.0000000000008" />
                <XVek X="0.6694801722986664" Y="0.1924442105817231" Z="0.7174688318753123" />
                <YVek X="-0.2585984216936966" Y="0.9658216896542196" Z="-0.01775725460192135" />
                <ZVek X="-0.6963642403200188" Y="-0.1736481776669303" Z="0.6963642403200191" />
                <Rot X="0" Y="0" Z="0" />
                <Ext-Achswerte EA3="0" />
            </Frame>
            <Frame>
                <Pos X="-1500.000000000001" Y="-22.9999999000002" Z="-440.0000000000014" />
                <XVek X="0.7094833682514552" Y="-0.0122241277311797" Z="0.7046161514440199" />
                <YVek X="-0.182636826731462" Y="0.962499272775453" Z="0.2005964591616364" />
                <ZVek X="-0.6806446500899218" Y="-0.2710087094687843" Z="0.6806446500899217" />
                <Rot X="0" Y="0" Z="0" />
                <Ext-Achswerte EA3="0" />
            </Frame>
        </Frames>
    </SNaht>
    <SNaht Name="AutoDetect_53_18" ID="-308367133" ZRotLock="0" WkzWkl="45" WkzName="MRW510_CDD_10GH">
        <Kontur>
            <Punkt X="-1490" Y="73.89999999999976" Z="-440">
                <Fl_Norm X="1" Y="0" Z="0" />
                <Fl_Norm X="0" Y="0" Z="1" />
                <Rot X="0" Y="0" Z="0" />
                <Ext-Achswerte EA3="0" />
            </Punkt>
            <Punkt X="-1490" Y="22.99999990000001" Z="-440">
                <Fl_Norm X="1" Y="0" Z="0" />
                <Fl_Norm X="0" Y="0" Z="1" />
                <Rot X="0" Y="0" Z="0" />
                <Ext-Achswerte EA3="0" />
            </Punkt>
        </Kontur>
        <Frames>
            <Frame>
                <Pos X="-1490.000000000003" Y="73.89999999999966" Z="-440.0000000000001" />
                <XVek X="-0.6694801722986662" Y="-0.1924442105817231" Z="0.7174688318753126" />
                <YVek X="0.2585984216936966" Y="-0.9658216896542196" Z="-0.01775725460192145" />
                <ZVek X="0.6963642403200191" Y="0.1736481776669304" Z="0.6963642403200189" />
                <Rot X="0" Y="0" Z="0" />
                <Ext-Achswerte EA3="0" />
            </Frame>
            <Frame>
                <Pos X="-1490" Y="22.99999989999969" Z="-439.9999999999994" />
                <XVek X="-0.7094833682505275" Y="0.01222412769781635" Z="0.7046161514455327" />
                <YVek X="0.18263682715014" Y="-0.9624992726183536" Z="0.2005964595342359" />
                <ZVek X="0.6806446499785452" Y="0.2710087100282349" Z="0.6806446499785449" />
                <Rot X="0" Y="0" Z="0" />
                <Ext-Achswerte EA3="0" />
            </Frame>
        </Frames>
    </SNaht>
    <SNaht Name="AutoDetect_54_19" ID="-308367010" ZRotLock="0" WkzWkl="45" WkzName="MRW510_CDD_10GH">
        <Kontur>
            <Punkt X="-1500" Y="73.90000000000022" Z="-440">
                <Fl_Norm X="-1" Y="0" Z="0" />
                <Fl_Norm X="0" Y="0" Z="1" />
                <Rot X="0" Y="0" Z="0" />
                <Ext-Achswerte EA3="0" />
            </Punkt>
            <Punkt X="-1500" Y="22.99999990000001" Z="-440">
                <Fl_Norm X="-1" Y="0" Z="0" />
                <Fl_Norm X="0" Y="0" Z="1" />
                <Rot X="0" Y="0" Z="0" />
                <Ext-Achswerte EA3="0" />
            </Punkt>
        </Kontur>
        <Frames>
            <Frame>
                <Pos X="-1500.000000000002" Y="73.9000000000004" Z="-440.0000000000011" />
                <XVek X="-0.6346155553801681" Y="0.3041531218414738" Z="-0.7104603967453825" />
                <YVek X="-0.3351715108314601" Y="-0.9366627935746352" Z="-0.1016015229212469" />
                <ZVek X="-0.696364240320019" Y="0.1736481776669304" Z="0.6963642403200189" />
                <Rot X="0" Y="0" Z="0" />
                <Ext-Achswerte EA3="0" />
            </Frame>
            <Frame>
                <Pos X="-1500.000000000002" Y="22.99999990000012" Z="-439.9999999999999" />
                <XVek X="-0.6391250575867735" Y="-0.01736515052514246" Z="-0.7689067643817049" />
                <YVek X="-0.122628044409189" Y="-0.9846546409478775" Z="0.1241676317893868" />
                <ZVek X="-0.759263803621035" Y="0.1736481776669307" Z="0.6271879996491265" />
                <Rot X="0" Y="0" Z="0" />
                <Ext-Achswerte EA3="0" />
            </Frame>
        </Frames>
    </SNaht>
    <SNaht Name="AutoDetect_26_20" ID="-308366823" ZRotLock="0" WkzWkl="45" WkzName="MRW510_CDD_10GH">
        <Kontur>
            <Punkt X="-3630" Y="2.999999900000006" Z="-328">
                <Fl_Norm X="1" Y="0" Z="0" />
                <Fl_Norm X="0" Y="1" Z="0" />
                <Rot X="90" Y="0" Z="0" />
                <Ext-Achswerte EA3="-90" />
            </Punkt>
            <Punkt X="-3630" Y="2.999999900000006" Z="-367.9999999999998">
                <Fl_Norm X="1" Y="0" Z="0" />
                <Fl_Norm X="0" Y="1" Z="0" />
                <Rot X="90" Y="0" Z="0" />
                <Ext-Achswerte EA3="-90" />
            </Punkt>
            <Punkt X="-3630" Y="2.999999900000006" Z="-419.9999999999999">
                <Fl_Norm X="1" Y="0" Z="0" />
                <Fl_Norm X="0" Y="1" Z="0" />
                <Rot X="90" Y="0" Z="0" />
                <Ext-Achswerte EA3="-90" />
            </Punkt>
        </Kontur>
        <Frames>
            <Frame>
                <Pos X="-3630.000000000002" Y="2.999999899999921" Z="-327.9999999999999" />
                <XVek X="0.07045688741618469" Y="-0.009275825200574871" Z="0.9974716968829098" />
                <YVek X="0.7042546354946766" Y="-0.7077094910109415" Z="-0.05632658978931933" />
                <ZVek X="0.7064426624998544" Y="0.7064426624998539" Z="-0.04333046503598009" />
                <Rot X="90" Y="0" Z="0" />
                <Ext-Achswerte EA3="-90" />
            </Frame>
            <Frame>
                <Pos X="-3630.000000000003" Y="2.99999990000083" Z="-367.9999999999999" />
                <XVek X="-0.2758330642013611" Y="0.03631411181929343" Z="0.9605193418021647" />
                <YVek X="0.6625654424257357" Y="-0.7167692307056007" Z="0.2173681310976623" />
                <ZVek X="0.6963642403200189" Y="0.6963642403200191" Z="0.1736481776669304" />
                <Rot X="90" Y="0" Z="0" />
                <Ext-Achswerte EA3="-90" />
            </Frame>
            <Frame>
                <Pos X="-3630.000000000005" Y="2.999999900001512" Z="-420.0000000000002" />
                <XVek X="-0.2758330642013611" Y="0.03631411181929343" Z="0.9605193418021647" />
                <YVek X="0.6625654424257357" Y="-0.7167692307056007" Z="0.2173681310976623" />
                <ZVek X="0.6963642403200189" Y="0.6963642403200191" Z="0.1736481776669304" />
                <Rot X="90" Y="0" Z="0" />
                <Ext-Achswerte EA3="-90" />
            </Frame>
        </Frames>
    </SNaht>
    <SNaht Name="AutoDetect_25_21" ID="-308366627" ZRotLock="0" WkzWkl="45" WkzName="MRW510_CDD_10GH">
        <Kontur>
            <Punkt X="-3640" Y="2.999999900000006" Z="-328">
                <Fl_Norm X="-1" Y="0" Z="0" />
                <Fl_Norm X="0" Y="1" Z="0" />
                <Rot X="90" Y="0" Z="0" />
                <Ext-Achswerte EA3="-90" />
            </Punkt>
            <Punkt X="-3640" Y="2.999999900000006" Z="-368.0000000000006">
                <Fl_Norm X="-1" Y="0" Z="0" />
                <Fl_Norm X="0" Y="1" Z="0" />
                <Rot X="90" Y="0" Z="0" />
                <Ext-Achswerte EA3="-90" />
            </Punkt>
            <Punkt X="-3640" Y="2.999999900000006" Z="-419.9999999999999">
                <Fl_Norm X="-1" Y="0" Z="0" />
                <Fl_Norm X="0" Y="1" Z="0" />
                <Rot X="90" Y="0" Z="0" />
                <Ext-Achswerte EA3="-90" />
            </Punkt>
        </Kontur>
        <Frames>
            <Frame>
                <Pos X="-3640" Y="2.999999899999239" Z="-328.0000000000003" />
                <XVek X="0.2817002737353337" Y="0.2237863856169022" Z="-0.9330405186217591" />
                <YVek X="-0.6493121570275566" Y="-0.6714767122535698" Z="-0.357089271243702" />
                <ZVek X="-0.7064266971977061" Y="0.7064266971977063" Z="-0.04384795289042116" />
                <Rot X="90" Y="0" Z="0" />
                <Ext-Achswerte EA3="-90" />
            </Frame>
            <Frame>
                <Pos X="-3640.000000000001" Y="2.99999990000083" Z="-368.0000000000007" />
                <XVek X="-0.1633251363530677" Y="0.08184251295467548" Z="-0.9831717565657161" />
                <YVek X="-0.698857456595245" Y="-0.7130067656598966" Z="0.05674158514210356" />
                <ZVek X="-0.696364240320019" Y="0.696364240320019" Z="0.1736481776669302" />
                <Rot X="90" Y="0" Z="0" />
                <Ext-Achswerte EA3="-90" />
            </Frame>
            <Frame>
                <Pos X="-3640.000000000002" Y="2.999999900003104" Z="-420.0000000000007" />
                <XVek X="-0.2419547857523648" Y="3.519794442636283e-16" Z="-0.970287525247814" />
                <YVek X="-0.6756735354111855" Y="-0.7176885430348755" Z="0.1684886605722382" />
                <ZVek X="-0.6963642403200186" Y="0.6963642403200192" Z="0.1736481776669304" />
                <Rot X="90" Y="0" Z="0" />
                <Ext-Achswerte EA3="-90" />
            </Frame>
        </Frames>
    </SNaht>
    <SNaht Name="AutoDetect_7_22" ID="-308366563" ZRotLock="0" WkzWkl="45" WkzName="MRW510_CDD_10GH">
        <Kontur>
            <Punkt X="-4334.331183390067" Y="3.000000000000114" Z="-322">
                <Fl_Norm X="0.9510564653401542" Y="0.3090171511982663" Z="0" />
                <Fl_Norm X="0" Y="1" Z="0" />
                <Rot X="90" Y="0" Z="0" />
                <Ext-Achswerte EA3="-90" />
            </Punkt>
            <Punkt X="-4334.331183390067" Y="3.000000000000114" Z="-362.0000000000003">
                <Fl_Norm X="0.9510564653401542" Y="0.3090171511982663" Z="0" />
                <Fl_Norm X="0" Y="1" Z="0" />
                <Rot X="90" Y="0" Z="0" />
                <Ext-Achswerte EA3="-90" />
            </Punkt>
            <Punkt X="-4334.331183390067" Y="3.000000000000114" Z="-416.0000000000004">
                <Fl_Norm X="0.9510564653401542" Y="0.3090171511982663" Z="0" />
                <Fl_Norm X="0" Y="1" Z="0" />
                <Rot X="90" Y="0" Z="0" />
                <Ext-Achswerte EA3="-90" />
            </Punkt>
        </Kontur>
        <Frames>
            <Frame>
                <Pos X="-4334.331183390072" Y="3.000000000001592" Z="-322.0000000000009" />
                <XVek X="0.1472227164613929" Y="5.551115123125785e-17" Z="0.9891033675798139" />
                <YVek X="0.7971564732740321" Y="-0.5919992840949486" Z="-0.1186524536129603" />
                <ZVek X="0.5855484855031526" Y="0.8059384887391023" Z="-0.08715574274765824" />
                <Rot X="90" Y="0" Z="0" />
                <Ext-Achswerte EA3="-90" />
            </Frame>
            <Frame>
                <Pos X="-4334.331183390068" Y="2.999999999999091" Z="-362.0000000000003" />
                <XVek X="-0.287335065897963" Y="1.627907992503155e-16" Z="0.9578301310281554" />
                <YVek X="0.7631284142775883" Y="-0.6043403617454594" Z="0.2289273913002569" />
                <ZVek X="0.5788554078762562" Y="0.7967262561039188" Z="0.1736481776669302" />
                <Rot X="90" Y="0" Z="0" />
                <Ext-Achswerte EA3="-90" />
            </Frame>
            <Frame>
                <Pos X="-4334.331183390068" Y="2.999999999999091" Z="-416.0000000000006" />
                <XVek X="-0.287335065897963" Y="1.627907992503155e-16" Z="0.9578301310281554" />
                <YVek X="0.7631284142775883" Y="-0.6043403617454594" Z="0.2289273913002569" />
                <ZVek X="0.5788554078762562" Y="0.7967262561039188" Z="0.1736481776669302" />
                <Rot X="90" Y="0" Z="0" />
                <Ext-Achswerte EA3="-90" />
            </Frame>
        </Frames>
    </SNaht>
    <SNaht Name="AutoDetect_9_23" ID="-308366466" ZRotLock="0" WkzWkl="45" WkzName="MRW510_CDD_10GH">
        <Kontur>
            <Punkt X="-3630" Y="-2.999999900000006" Z="-328">
                <Fl_Norm X="1" Y="0" Z="0" />
                <Fl_Norm X="0" Y="-1" Z="0" />
                <Rot X="-90" Y="0" Z="-0" />
                <Ext-Achswerte EA3="90" />
            </Punkt>
            <Punkt X="-3630" Y="-2.999999900000006" Z="-368.0000000000001">
                <Fl_Norm X="1" Y="0" Z="0" />
                <Fl_Norm X="0" Y="-1" Z="0" />
                <Rot X="-90" Y="0" Z="-0" />
                <Ext-Achswerte EA3="90" />
            </Punkt>
            <Punkt X="-3630" Y="-2.999999900000006" Z="-419.9999999999999">
                <Fl_Norm X="1" Y="0" Z="0" />
                <Fl_Norm X="0" Y="-1" Z="0" />
                <Rot X="-90" Y="0" Z="-0" />
                <Ext-Achswerte EA3="90" />
            </Punkt>
        </Kontur>
        <Frames>
            <Frame>
                <Pos X="-3630.000000000004" Y="-2.99999989999742" Z="-328.0000000000001" />
                <XVek X="-0.2810677798993105" Y="-0.2236071967442631" Z="-0.9332741958645622" />
                <YVek X="0.6495743144153225" Y="0.6715249127246408" Z="-0.3565213901605727" />
                <ZVek X="0.7064376215592826" Y="-0.7064376215592825" Z="-0.04349452484310615" />
                <Rot X="-90" Y="0" Z="-0" />
                <Ext-Achswerte EA3="90" />
            </Frame>
            <Frame>
                <Pos X="-3630.000000000002" Y="-2.999999900001512" Z="-368.0000000000001" />
                <XVek X="0.1633251363530679" Y="-0.08184251295467551" Z="-0.983171756565716" />
                <YVek X="0.6988574565952448" Y="0.7130067656598967" Z="0.05674158514210364" />
                <ZVek X="0.696364240320019" Y="-0.6963642403200188" Z="0.1736481776669304" />
                <Rot X="-90" Y="0" Z="-0" />
                <Ext-Achswerte EA3="90" />
            </Frame>
            <Frame>
                <Pos X="-3630.000000000003" Y="-2.999999900001967" Z="-419.9999999999999" />
                <XVek X="0.2419547857523648" Y="-2.914335439641036e-16" Z="-0.970287525247814" />
                <YVek X="0.6756735354111852" Y="0.7176885430348759" Z="0.1684886605722382" />
                <ZVek X="0.696364240320019" Y="-0.696364240320019" Z="0.1736481776669304" />
                <Rot X="-90" Y="0" Z="-0" />
                <Ext-Achswerte EA3="90" />
            </Frame>
        </Frames>
    </SNaht>
    <SNaht Name="AutoDetect_10_24" ID="-308366392" ZRotLock="0" WkzWkl="45" WkzName="MRW510_CDD_10GH">
        <Kontur>
            <Punkt X="-3640" Y="-2.999999900000006" Z="-328">
                <Fl_Norm X="-1" Y="0" Z="0" />
                <Fl_Norm X="0" Y="-1" Z="0" />
                <Rot X="-90" Y="0" Z="-0" />
                <Ext-Achswerte EA3="90" />
            </Punkt>
            <Punkt X="-3640" Y="-2.999999900000006" Z="-368.0000000000007">
                <Fl_Norm X="-1" Y="0" Z="0" />
                <Fl_Norm X="0" Y="-1" Z="0" />
                <Rot X="-90" Y="0" Z="-0" />
                <Ext-Achswerte EA3="90" />
            </Punkt>
            <Punkt X="-3640" Y="-2.999999900000006" Z="-419.9999999999999">
                <Fl_Norm X="-1" Y="0" Z="0" />
                <Fl_Norm X="0" Y="-1" Z="0" />
                <Rot X="-90" Y="0" Z="-0" />
                <Ext-Achswerte EA3="90" />
            </Punkt>
        </Kontur>
        <Frames>
            <Frame>
                <Pos X="-3640.000000000002" Y="-2.999999899998784" Z="-328" />
                <XVek X="-0.07110826106969781" Y="0.009361580168922015" Z="0.9974246718546642" />
                <YVek X="-0.704201586505236" Y="0.7077207217862052" Z="-0.05684633249314733" />
                <ZVek X="-0.7064302801912956" Y="-0.7064302801912965" Z="-0.04373235024205761" />
                <Rot X="-90" Y="0" Z="-0" />
                <Ext-Achswerte EA3="90" />
            </Frame>
            <Frame>
                <Pos X="-3640.000000000001" Y="-2.999999899999466" Z="-368.0000000000009" />
                <XVek X="0.2758330642013614" Y="-0.03631411181929374" Z="0.9605193418021646" />
                <YVek X="-0.6625654424257355" Y="0.7167692307056008" Z="0.2173681310976628" />
                <ZVek X="-0.696364240320019" Y="-0.696364240320019" Z="0.1736481776669304" />
                <Rot X="-90" Y="0" Z="-0" />
                <Ext-Achswerte EA3="90" />
            </Frame>
            <Frame>
                <Pos X="-3640.000000000002" Y="-2.999999900000148" Z="-420.0000000000011" />
                <XVek X="0.2758330642013614" Y="-0.0363141118192937" Z="0.9605193418021646" />
                <YVek X="-0.6625654424257355" Y="0.7167692307056007" Z="0.2173681310976627" />
                <ZVek X="-0.696364240320019" Y="-0.6963642403200189" Z="0.1736481776669305" />
                <Rot X="-90" Y="0" Z="-0" />
                <Ext-Achswerte EA3="90" />
            </Frame>
        </Frames>
    </SNaht>
    <SNaht Name="AutoDetect_8_25" ID="-308366332" ZRotLock="0" WkzWkl="45" WkzName="MRW510_CDD_10GH">
        <Kontur>
            <Punkt X="-4332.381665212669" Y="-2.999999999999886" Z="-426">
                <Fl_Norm X="0.9510564653401542" Y="0.3090171511982663" Z="0" />
                <Fl_Norm X="0" Y="-1" Z="0" />
                <Rot X="-90" Y="0" Z="-0" />
                <Ext-Achswerte EA3="90" />
            </Punkt>
            <Punkt X="-4332.381665212669" Y="-2.999999999999886" Z="-386.0000000000011">
                <Fl_Norm X="0.9510564653401542" Y="0.3090171511982663" Z="0" />
                <Fl_Norm X="0" Y="-1" Z="0" />
                <Rot X="-90" Y="0" Z="-0" />
                <Ext-Achswerte EA3="90" />
            </Punkt>
            <Punkt X="-4332.381665212669" Y="-2.999999999999886" Z="-331.9999999999998">
                <Fl_Norm X="0.9510564653401542" Y="0.3090171511982663" Z="0" />
                <Fl_Norm X="0" Y="-1" Z="0" />
                <Rot X="-90" Y="0" Z="-0" />
                <Ext-Achswerte EA3="90" />
            </Punkt>
        </Kontur>
        <Frames>
            <Frame>
                <Pos X="-4332.381665212674" Y="-3" Z="-426.0000000000006" />
                <XVek X="0.009528591273177791" Y="-0.1343729228636013" Z="-0.9908850203476897" />
                <YVek X="0.5919225948697009" Y="0.7994228472629846" Z="-0.102716858191159" />
                <ZVek X="0.8059384887391025" Y="-0.5855484855031524" Z="0.08715574274765807" />
                <Rot X="-90" Y="0" Z="-0" />
                <Ext-Achswerte EA3="90" />
            </Frame>
            <Frame>
                <Pos X="-4332.381665212672" Y="-2.999999999999091" Z="-386.000000000001" />
                <XVek X="-0.3758886322920167" Y="-0.2496593991963459" Z="-0.8924000899297112" />
                <YVek X="0.4732177183372046" Y="0.7762709585997228" Z="-0.4164953659843018" />
                <ZVek X="0.7967262561039188" Y="-0.5788554078762563" Z="-0.1736481776669303" />
                <Rot X="-90" Y="0" Z="-0" />
                <Ext-Achswerte EA3="90" />
            </Frame>
            <Frame>
                <Pos X="-4332.381665212675" Y="-2.999999999995907" Z="-331.9999999999995" />
                <XVek X="-0.2954124152464469" Y="-0.1223638288884707" Z="-0.9475012392065848" />
                <YVek X="0.5272179603853548" Y="0.8061969425346178" Z="-0.2684915493920438" />
                <ZVek X="0.7967262561039186" Y="-0.5788554078762564" Z="-0.1736481776669303" />
                <Rot X="-90" Y="0" Z="-0" />
                <Ext-Achswerte EA3="90" />
            </Frame>
        </Frames>
    </SNaht>
    <SNaht Name="AutoDetect_11_26" ID="-308366244" ZRotLock="0" WkzWkl="45" WkzName="MRW510_CDD_10GH">
        <Kontur>
            <Punkt X="-3630" Y="-73.89999999999954" Z="-308">
                <Fl_Norm X="1" Y="0" Z="0" />
                <Fl_Norm X="0" Y="0" Z="-1" />
                <Rot X="180" Y="0" Z="0" />
                <Ext-Achswerte EA3="180" />
            </Punkt>
            <Punkt X="-3630" Y="-22.9999999" Z="-308">
                <Fl_Norm X="1" Y="0" Z="0" />
                <Fl_Norm X="0" Y="0" Z="-1" />
                <Rot X="180" Y="0" Z="0" />
                <Ext-Achswerte EA3="180" />
            </Punkt>
        </Kontur>
        <Frames>
            <Frame>
                <Pos X="-3630.000000000007" Y="-73.89999999999941" Z="-308.000000000003" />
                <XVek X="-0.6346155553801688" Y="0.3041531218414723" Z="-0.7104603967453826" />
                <YVek X="0.3351715108314589" Y="0.9366627935746358" Z="0.101601522921246" />
                <ZVek X="0.696364240320019" Y="-0.1736481776669301" Z="-0.6963642403200189" />
                <Rot X="180" Y="0" Z="0" />
                <Ext-Achswerte EA3="180" />
            </Frame>
            <Frame>
                <Pos X="-3630.000000000001" Y="-22.99999990000049" Z="-308.0000000000034" />
                <XVek X="-0.6734466693769956" Y="0.1291860736071021" Z="-0.7278602488740623" />
                <YVek X="0.2953113449255276" Y="0.9496486426634831" Z="-0.1046836426844241" />
                <ZVek X="0.6776878286226687" Y="-0.2854442395169055" Z="-0.677687828622669" />
                <Rot X="180" Y="0" Z="0" />
                <Ext-Achswerte EA3="180" />
            </Frame>
        </Frames>
    </SNaht>
    <SNaht Name="AutoDetect_13_27" ID="-308366201" ZRotLock="0" WkzWkl="45" WkzName="MRW510_CDD_10GH">
        <Kontur>
            <Punkt X="-3640" Y="-73.89999999999975" Z="-308">
                <Fl_Norm X="-1" Y="0" Z="0" />
                <Fl_Norm X="0" Y="0" Z="-1" />
                <Rot X="180" Y="0" Z="0" />
                <Ext-Achswerte EA3="180" />
            </Punkt>
            <Punkt X="-3640" Y="-22.99999990000001" Z="-308">
                <Fl_Norm X="-1" Y="0" Z="0" />
                <Fl_Norm X="0" Y="0" Z="-1" />
                <Rot X="180" Y="0" Z="0" />
                <Ext-Achswerte EA3="180" />
            </Punkt>
        </Kontur>
        <Frames>
            <Frame>
                <Pos X="-3640.000000000003" Y="-73.89999999999952" Z="-307.9999999999975" />
                <XVek X="-0.6309120413685944" Y="-0.3143786283125719" Z="0.7093067560064678" />
                <YVek X="-0.3420918602650986" Y="0.9332804446966946" Z="0.1093653084259545" />
                <ZVek X="-0.6963642403200189" Y="-0.1736481776669301" Z="-0.6963642403200189" />
                <Rot X="180" Y="0" Z="0" />
                <Ext-Achswerte EA3="180" />
            </Frame>
            <Frame>
                <Pos X="-3640.000000000003" Y="-22.99999990000015" Z="-308" />
                <XVek X="-0.6376028314939224" Y="0.006595559129886537" Z="0.7703370222640847" />
                <YVek X="-0.1296318936522378" Y="0.9847856665248121" Z="-0.115727106398702" />
                <ZVek X="-0.759380142892259" Y="-0.1736481776669302" Z="-0.6270471345711474" />
                <Rot X="180" Y="0" Z="0" />
                <Ext-Achswerte EA3="180" />
            </Frame>
        </Frames>
    </SNaht>
    <SNaht Name="AutoDetect_8_28" ID="-308366151" ZRotLock="0" WkzWkl="45" WkzName="MRW510_CDD_10GH">
        <Kontur>
            <Punkt X="-4309.249442538609" Y="-74.19366090222792" Z="-307.0000000000001">
                <Fl_Norm X="0.9510564653401542" Y="0.3090171511982663" Z="0" />
                <Fl_Norm X="0" Y="0" Z="-1" />
                <Rot X="180" Y="0" Z="0" />
                <Ext-Achswerte EA3="180" />
            </Punkt>
            <Punkt X="-4324.417699825279" Y="-27.51056516340262" Z="-307">
                <Fl_Norm X="0.9510564653401542" Y="0.3090171511982663" Z="0" />
                <Fl_Norm X="0" Y="0" Z="-1" />
                <Rot X="180" Y="0" Z="0" />
                <Ext-Achswerte EA3="180" />
            </Punkt>
        </Kontur>
        <Frames>
            <Frame>
                <Pos X="-4309.249442538618" Y="-74.19366090222914" Z="-307.0000000000034" />
                <XVek X="-0.6857331864117098" Y="-0.04171778320271591" Z="-0.726656468778951" />
                <YVek X="-0.01310096341040184" Y="0.9989017813811536" Z="-0.04498439630891302" />
                <ZVek X="0.7277350904081531" Y="-0.02132739361031324" Z="-0.6855266446101334" />
                <Rot X="180" Y="0" Z="0" />
                <Ext-Achswerte EA3="180" />
            </Frame>
            <Frame>
                <Pos X="-4324.417699825282" Y="-27.5105651634027" Z="-306.9999999999989" />
                <XVek X="-0.6518957575412331" Y="-0.04844258857973013" Z="-0.7567596956177284" />
                <YVek X="0.1743429827377873" Y="0.9616494221143984" Z="-0.2117425637823796" />
                <ZVek X="0.7379948818723837" Y="-0.2699698215703719" Z="-0.6184495531338252" />
                <Rot X="180" Y="0" Z="0" />
                <Ext-Achswerte EA3="180" />
            </Frame>
        </Frames>
    </SNaht>
    <SNaht Name="AutoDetect_29_29" ID="-308366060" ZRotLock="0" WkzWkl="45" WkzName="MRW510_CDD_10GH">
        <Kontur>
            <Punkt X="-3630" Y="73.8999999999993" Z="-308">
                <Fl_Norm X="1" Y="0" Z="0" />
                <Fl_Norm X="0" Y="0" Z="-1" />
                <Rot X="180" Y="0" Z="0" />
                <Ext-Achswerte EA3="180" />
            </Punkt>
            <Punkt X="-3630" Y="22.99999990000001" Z="-308">
                <Fl_Norm X="1" Y="0" Z="0" />
                <Fl_Norm X="0" Y="0" Z="-1" />
                <Rot X="180" Y="0" Z="0" />
                <Ext-Achswerte EA3="180" />
            </Punkt>
        </Kontur>
        <Frames>
            <Frame>
                <Pos X="-3630.000000000006" Y="73.89999999999918" Z="-308.000000000002" />
                <XVek X="0.630912041368594" Y="0.3143786283125727" Z="0.7093067560064678" />
                <YVek X="0.342091860265099" Y="-0.9332804446966944" Z="0.1093653084259554" />
                <ZVek X="0.6963642403200193" Y="0.1736481776669298" Z="-0.6963642403200188" />
                <Rot X="180" Y="0" Z="0" />
                <Ext-Achswerte EA3="180" />
            </Frame>
            <Frame>
                <Pos X="-3630.000000000005" Y="22.99999989999895" Z="-308.000000000002" />
                <XVek X="0.6376028314903305" Y="-0.006595559129886908" Z="0.7703370222670577" />
                <YVek X="0.1296318936527778" Y="-0.9847856665248119" Z="-0.1157271063980983" />
                <ZVek X="0.7593801428951827" Y="0.1736481776669309" Z="-0.6270471345676064" />
                <Rot X="180" Y="0" Z="0" />
                <Ext-Achswerte EA3="180" />
            </Frame>
        </Frames>
    </SNaht>
    <SNaht Name="AutoDetect_30_30" ID="-308365924" ZRotLock="0" WkzWkl="45" WkzName="MRW510_CDD_10GH">
        <Kontur>
            <Punkt X="-3640" Y="73.89999999999981" Z="-308.0000000000001">
                <Fl_Norm X="-1" Y="0" Z="0" />
                <Fl_Norm X="0" Y="0" Z="-1" />
                <Rot X="180" Y="0" Z="0" />
                <Ext-Achswerte EA3="180" />
            </Punkt>
            <Punkt X="-3640" Y="22.99999990000001" Z="-308">
                <Fl_Norm X="-1" Y="0" Z="0" />
                <Fl_Norm X="0" Y="0" Z="-1" />
                <Rot X="180" Y="0" Z="0" />
                <Ext-Achswerte EA3="180" />
            </Punkt>
        </Kontur>
        <Frames>
            <Frame>
                <Pos X="-3640" Y="73.89999999999947" Z="-307.9999999999993" />
                <XVek X="0.6346155553801685" Y="-0.3041531218414728" Z="-0.7104603967453826" />
                <YVek X="-0.3351715108314596" Y="-0.9366627935746356" Z="0.101601522921246" />
                <ZVek X="-0.6963642403200189" Y="0.1736481776669306" Z="-0.6963642403200189" />
                <Rot X="180" Y="0" Z="0" />
                <Ext-Achswerte EA3="180" />
            </Frame>
            <Frame>
                <Pos X="-3640.000000000005" Y="22.99999989999947" Z="-307.9999999999995" />
                <XVek X="0.6734466691044697" Y="-0.1291860737208636" Z="-0.7278602491060233" />
                <YVek X="-0.2953113466102288" Y="-0.9496486419867527" Z="-0.1046836440709329" />
                <ZVek X="-0.6776878281593584" Y="0.285444241716844" Z="-0.6776878281593582" />
                <Rot X="180" Y="0" Z="0" />
                <Ext-Achswerte EA3="180" />
            </Frame>
        </Frames>
    </SNaht>
    <SNaht Name="AutoDetect_6_31" ID="-308365783" ZRotLock="0" WkzWkl="45" WkzName="MRW510_CDD_10GH">
        <Kontur>
            <Punkt X="-4357.495898043153" Y="74.2936609311645" Z="-450">
                <Fl_Norm X="-0" Y="-3.944304526105059e-32" Z="-1" />
                <Fl_Norm X="0.9510564653401542" Y="0.3090171511982663" Z="0" />
                <Rot X="180" Y="0" Z="0" />
                <Ext-Achswerte EA3="180" />
            </Punkt>
            <Punkt X="-4309.216950568985" Y="-74.29366090222904" Z="-450">
                <Fl_Norm X="-0" Y="-3.944304526105059e-32" Z="-1" />
                <Fl_Norm X="0.9510564653401542" Y="0.3090171511982663" Z="0" />
                <Rot X="180" Y="0" Z="0" />
                <Ext-Achswerte EA3="180" />
            </Punkt>
        </Kontur>
        <Frames>
            <Frame>
                <Pos X="-4357.495898043155" Y="74.29366093116312" Z="-450.0000000000014" />
                <XVek X="-0.7151062958258918" Y="0.643204380841675" Z="-0.2736989406925967" />
                <YVek X="0.3438064896946545" Y="0.6645534914792148" Z="0.663449888542175" />
                <ZVek X="0.6086214614306755" Y="0.3803377202288284" Z="-0.6963642260032649" />
                <Rot X="180" Y="0" Z="0" />
                <Ext-Achswerte EA3="180" />
            </Frame>
            <Frame>
                <Pos X="-4309.216950568986" Y="-74.29366090222959" Z="-450.000000000002" />
                <XVek X="-0.7151062958258918" Y="0.643204380841675" Z="-0.2736989406925967" />
                <YVek X="0.3438064896946545" Y="0.6645534914792148" Z="0.663449888542175" />
                <ZVek X="0.6086214614306755" Y="0.3803377202288284" Z="-0.6963642260032649" />
                <Rot X="180" Y="0" Z="0" />
                <Ext-Achswerte EA3="180" />
            </Frame>
        </Frames>
    </SNaht>
    <SNaht Name="AutoDetect_7_32" ID="-308365498" ZRotLock="0" WkzWkl="45" WkzName="MRW510_CDD_10GH">
        <Kontur>
            <Punkt X="-4357.46340606398" Y="74.19366090177439" Z="-307">
                <Fl_Norm X="0.9510564653401542" Y="0.3090171511982663" Z="0" />
                <Fl_Norm X="0" Y="0" Z="-1" />
                <Rot X="180" Y="0" Z="0" />
                <Ext-Achswerte EA3="180" />
            </Punkt>
            <Punkt X="-4342.295148777311" Y="27.51056516295137" Z="-307">
                <Fl_Norm X="0.9510564653401542" Y="0.3090171511982663" Z="0" />
                <Fl_Norm X="0" Y="0" Z="-1" />
                <Rot X="180" Y="0" Z="0" />
                <Ext-Achswerte EA3="180" />
            </Punkt>
        </Kontur>
        <Frames>
            <Frame>
                <Pos X="-4357.463406063983" Y="74.19366090177277" Z="-307.000000000002" />
                <XVek X="0.61990349445653" Y="0.3198912030411751" Z="0.7165118811139509" />
                <YVek X="0.4952772868006388" Y="-0.8677631244489061" Z="-0.04108003196286755" />
                <ZVek X="0.6086214478146336" Y="0.380337715804707" Z="-0.696364240320019" />
                <Rot X="180" Y="0" Z="0" />
                <Ext-Achswerte EA3="180" />
            </Frame>
            <Frame>
                <Pos X="-4342.29514877731" Y="27.51056516295148" Z="-307.000000000002" />
                <XVek X="0.61990349445653" Y="0.3198912030411751" Z="0.7165118811139509" />
                <YVek X="0.4952772868006388" Y="-0.8677631244489061" Z="-0.04108003196286755" />
                <ZVek X="0.6086214478146336" Y="0.380337715804707" Z="-0.696364240320019" />
                <Rot X="180" Y="0" Z="0" />
                <Ext-Achswerte EA3="180" />
            </Frame>
        </Frames>
    </SNaht>
    <SNaht Name="AutoDetect_14_33" ID="-308365226" ZRotLock="0" WkzWkl="45" WkzName="MRW510_CDD_10GH">
        <Kontur>
            <Punkt X="-3630" Y="-73.89999999999969" Z="-440">
                <Fl_Norm X="1" Y="0" Z="0" />
                <Fl_Norm X="0" Y="0" Z="1" />
                <Rot X="0" Y="0" Z="0" />
                <Ext-Achswerte EA3="0" />
            </Punkt>
            <Punkt X="-3630" Y="-22.99999989999999" Z="-440">
                <Fl_Norm X="1" Y="0" Z="0" />
                <Fl_Norm X="0" Y="0" Z="1" />
                <Rot X="0" Y="0" Z="0" />
                <Ext-Achswerte EA3="0" />
            </Punkt>
        </Kontur>
        <Frames>
            <Frame>
                <Pos X="-3630.000000000005" Y="-73.89999999999912" Z="-439.9999999999968" />
                <XVek X="0.6346155553801681" Y="-0.3041531218414738" Z="-0.7104603967453825" />
                <YVek X="0.3351715108314601" Y="0.9366627935746353" Z="-0.101601522921247" />
                <ZVek X="0.696364240320019" Y="-0.1736481776669304" Z="0.6963642403200189" />
                <Rot X="0" Y="0" Z="0" />
                <Ext-Achswerte EA3="0" />
            </Frame>
            <Frame>
                <Pos X="-3630.000000000002" Y="-22.99999990000083" Z="-439.9999999999989" />
                <XVek X="0.6391250575880301" Y="0.01736515052514295" Z="-0.7689067643806604" />
                <YVek X="0.1226280444089855" Y="0.9846546409478774" Z="0.1241676317895874" />
                <ZVek X="0.75926380362001" Y="-0.1736481776669304" Z="0.6271879996503673" />
                <Rot X="0" Y="0" Z="0" />
                <Ext-Achswerte EA3="0" />
            </Frame>
        </Frames>
    </SNaht>
    <SNaht Name="AutoDetect_12_34" ID="-308365058" ZRotLock="0" WkzWkl="45" WkzName="MRW510_CDD_10GH">
        <Kontur>
            <Punkt X="-3640" Y="-73.89999999999992" Z="-440">
                <Fl_Norm X="-1" Y="0" Z="0" />
                <Fl_Norm X="0" Y="0" Z="1" />
                <Rot X="0" Y="0" Z="0" />
                <Ext-Achswerte EA3="0" />
            </Punkt>
            <Punkt X="-3640" Y="-22.99999990000002" Z="-440">
                <Fl_Norm X="-1" Y="0" Z="0" />
                <Fl_Norm X="0" Y="0" Z="1" />
                <Rot X="0" Y="0" Z="0" />
                <Ext-Achswerte EA3="0" />
            </Punkt>
        </Kontur>
        <Frames>
            <Frame>
                <Pos X="-3640.000000000005" Y="-73.90000000000026" Z="-440.0000000000043" />
                <XVek X="0.6694801722986667" Y="0.1924442105817226" Z="0.7174688318753122" />
                <YVek X="-0.2585984216936962" Y="0.9658216896542197" Z="-0.01775725460192103" />
                <ZVek X="-0.6963642403200186" Y="-0.1736481776669302" Z="0.6963642403200193" />
                <Rot X="0" Y="0" Z="0" />
                <Ext-Achswerte EA3="0" />
            </Frame>
            <Frame>
                <Pos X="-3640.000000000001" Y="-22.99999990000094" Z="-440.000000000002" />
                <XVek X="0.7094833682514537" Y="-0.01222412773112572" Z="0.7046161514440221" />
                <YVek X="-0.1826368267321404" Y="0.9624992727751984" Z="0.2005964591622403" />
                <ZVek X="-0.6806446500897412" Y="-0.2710087094696909" Z="0.6806446500897414" />
                <Rot X="0" Y="0" Z="0" />
                <Ext-Achswerte EA3="0" />
            </Frame>
        </Frames>
    </SNaht>
    <SNaht Name="AutoDetect_8_35" ID="-308364897" ZRotLock="0" WkzWkl="45" WkzName="MRW510_CDD_10GH">
        <Kontur>
            <Punkt X="-4309.249442538608" Y="-74.19366090222857" Z="-440.9999999999999">
                <Fl_Norm X="0.9510564653401542" Y="0.3090171511982663" Z="0" />
                <Fl_Norm X="0" Y="0" Z="1" />
                <Rot X="0" Y="0" Z="0" />
                <Ext-Achswerte EA3="0" />
            </Punkt>
            <Punkt X="-4324.41769982528" Y="-27.5105651634026" Z="-440.9999999999999">
                <Fl_Norm X="0.9510564653401542" Y="0.3090171511982663" Z="0" />
                <Fl_Norm X="0" Y="0" Z="1" />
                <Rot X="0" Y="0" Z="0" />
                <Ext-Achswerte EA3="0" />
            </Punkt>
        </Kontur>
        <Frames>
            <Frame>
                <Pos X="-4309.24944253861" Y="-74.19366090222871" Z="-440.999999999998" />
                <XVek X="0.5570751209565464" Y="-0.2878558208371237" Z="-0.7789777506587944" />
                <YVek X="0.2382367467506959" Y="0.9539730438340946" Z="-0.1821501691889341" />
                <ZVek X="0.7955567623425081" Y="-0.08410979757494497" Z="0.6000124830726505" />
                <Rot X="0" Y="0" Z="0" />
                <Ext-Achswerte EA3="0" />
            </Frame>
            <Frame>
                <Pos X="-4324.417699825281" Y="-27.51056516340282" Z="-440.9999999999998" />
                <XVek X="0.5488872120552502" Y="-0.2929679021943115" Z="-0.7828745983400401" />
                <YVek X="0.392538383820463" Y="0.9172164977392884" Z="-0.06802582967147644" />
                <ZVek X="0.7379948818723838" Y="-0.2699698215703715" Z="0.6184495531338252" />
                <Rot X="0" Y="0" Z="0" />
                <Ext-Achswerte EA3="0" />
            </Frame>
        </Frames>
    </SNaht>
    <SNaht Name="AutoDetect_27_36" ID="-308364692" ZRotLock="0" WkzWkl="45" WkzName="MRW510_CDD_10GH">
        <Kontur>
            <Punkt X="-3630" Y="73.89999999999968" Z="-440">
                <Fl_Norm X="1" Y="0" Z="0" />
                <Fl_Norm X="0" Y="0" Z="1" />
                <Rot X="0" Y="0" Z="0" />
                <Ext-Achswerte EA3="0" />
            </Punkt>
            <Punkt X="-3630" Y="22.99999990000001" Z="-440">
                <Fl_Norm X="1" Y="0" Z="0" />
                <Fl_Norm X="0" Y="0" Z="1" />
                <Rot X="0" Y="0" Z="0" />
                <Ext-Achswerte EA3="0" />
            </Punkt>
        </Kontur>
        <Frames>
            <Frame>
                <Pos X="-3630.000000000008" Y="73.8999999999993" Z="-439.9999999999961" />
                <XVek X="-0.6694801722986664" Y="-0.1924442105817231" Z="0.7174688318753123" />
                <YVek X="0.2585984216936966" Y="-0.9658216896542196" Z="-0.01775725460192145" />
                <ZVek X="0.6963642403200188" Y="0.1736481776669303" Z="0.6963642403200191" />
                <Rot X="0" Y="0" Z="0" />
                <Ext-Achswerte EA3="0" />
            </Frame>
            <Frame>
                <Pos X="-3630" Y="22.99999989999958" Z="-439.9999999999984" />
                <XVek X="-0.7094833682639609" Y="0.01222412818105105" Z="0.7046161514236231" />
                <YVek X="0.1826368210859962" Y="-0.9624992748937875" Z="0.2005964541374926" />
                <ZVek X="0.6806446515917295" Y="0.2710087019251348" Z="0.6806446515917294" />
                <Rot X="0" Y="0" Z="0" />
                <Ext-Achswerte EA3="0" />
            </Frame>
        </Frames>
    </SNaht>
    <SNaht Name="AutoDetect_28_37" ID="-308364464" ZRotLock="0" WkzWkl="45" WkzName="MRW510_CDD_10GH">
        <Kontur>
            <Punkt X="-3640" Y="73.9000000000003" Z="-440">
                <Fl_Norm X="-1" Y="0" Z="0" />
                <Fl_Norm X="0" Y="0" Z="1" />
                <Rot X="0" Y="0" Z="0" />
                <Ext-Achswerte EA3="0" />
            </Punkt>
            <Punkt X="-3640" Y="22.99999990000001" Z="-440">
                <Fl_Norm X="-1" Y="0" Z="0" />
                <Fl_Norm X="0" Y="0" Z="1" />
                <Rot X="0" Y="0" Z="0" />
                <Ext-Achswerte EA3="0" />
            </Punkt>
        </Kontur>
        <Frames>
            <Frame>
                <Pos X="-3640.000000000002" Y="73.90000000000043" Z="-440.0000000000023" />
                <XVek X="-0.6346155553801681" Y="0.3041531218414738" Z="-0.7104603967453825" />
                <YVek X="-0.3351715108314601" Y="-0.9366627935746352" Z="-0.1016015229212469" />
                <ZVek X="-0.696364240320019" Y="0.1736481776669304" Z="0.6963642403200189" />
                <Rot X="0" Y="0" Z="0" />
                <Ext-Achswerte EA3="0" />
            </Frame>
            <Frame>
                <Pos X="-3639.999999999999" Y="22.99999989999941" Z="-440.0000000000002" />
                <XVek X="-0.6391250575862254" Y="-0.01736515052514234" Z="-0.7689067643821604" />
                <YVek X="-0.1226280444092773" Y="-0.9846546409478775" Z="0.1241676317892991" />
                <ZVek X="-0.7592638036214819" Y="0.1736481776669303" Z="0.6271879996485853" />
                <Rot X="0" Y="0" Z="0" />
                <Ext-Achswerte EA3="0" />
            </Frame>
        </Frames>
    </SNaht>
    <SNaht Name="AutoDetect_5_38" ID="-308364303" ZRotLock="0" WkzWkl="45" WkzName="MRW510_CDD_10GH">
        <Kontur>
            <Punkt X="-4357.495898043153" Y="74.2936609311645" Z="-298">
                <Fl_Norm X="0" Y="0" Z="1" />
                <Fl_Norm X="0.9510564653401542" Y="0.3090171511982663" Z="0" />
                <Rot X="0" Y="0" Z="0" />
                <Ext-Achswerte EA3="0" />
            </Punkt>
            <Punkt X="-4309.216950568986" Y="-74.29366090222889" Z="-298">
                <Fl_Norm X="0" Y="0" Z="1" />
                <Fl_Norm X="0.9510564653401542" Y="0.3090171511982663" Z="0" />
                <Rot X="0" Y="0" Z="0" />
                <Ext-Achswerte EA3="0" />
            </Punkt>
        </Kontur>
        <Frames>
            <Frame>
                <Pos X="-4357.495898043155" Y="74.29366093116369" Z="-297.999999999998" />
                <XVek X="0.5299481461119568" Y="-0.848030048071706" Z="8.78914994024407e-17" />
                <YVek X="0.5905377880529652" Y="0.369036930589118" Z="-0.7176885569262434" />
                <ZVek X="0.6086214614306755" Y="0.3803377202288284" Z="0.696364226003265" />
                <Rot X="0" Y="0" Z="0" />
                <Ext-Achswerte EA3="0" />
            </Frame>
            <Frame>
                <Pos X="-4309.216950568989" Y="-74.29366090222891" Z="-297.999999999998" />
                <XVek X="0.5299481461119568" Y="-0.848030048071706" Z="8.78914994024407e-17" />
                <YVek X="0.5905377880529652" Y="0.369036930589118" Z="-0.7176885569262434" />
                <ZVek X="0.6086214614306755" Y="0.3803377202288284" Z="0.696364226003265" />
                <Rot X="0" Y="0" Z="0" />
                <Ext-Achswerte EA3="0" />
            </Frame>
        </Frames>
    </SNaht>
    <SNaht Name="AutoDetect_7_39" ID="-308364167" ZRotLock="0" WkzWkl="45" WkzName="MRW510_CDD_10GH">
        <Kontur>
            <Punkt X="-4357.46340606398" Y="74.19366090177593" Z="-440.9999999999999">
                <Fl_Norm X="0.9510564653401542" Y="0.3090171511982663" Z="0" />
                <Fl_Norm X="0" Y="0" Z="1" />
                <Rot X="0" Y="0" Z="0" />
                <Ext-Achswerte EA3="0" />
            </Punkt>
            <Punkt X="-4342.29514877731" Y="27.51056516295245" Z="-441">
                <Fl_Norm X="0.9510564653401542" Y="0.3090171511982663" Z="0" />
                <Fl_Norm X="0" Y="0" Z="1" />
                <Rot X="0" Y="0" Z="0" />
                <Ext-Achswerte EA3="0" />
            </Punkt>
        </Kontur>
        <Frames>
            <Frame>
                <Pos X="-4357.463406063982" Y="74.19366090177596" Z="-441.0000000000005" />
                <XVek X="-0.6199034944565297" Y="-0.3198912030411754" Z="0.716511881113951" />
                <YVek X="0.4952772868006389" Y="-0.867763124448906" Z="0.04108003196286716" />
                <ZVek X="0.6086214478146337" Y="0.3803377158047069" Z="0.6963642403200189" />
                <Rot X="0" Y="0" Z="0" />
                <Ext-Achswerte EA3="0" />
            </Frame>
            <Frame>
                <Pos X="-4342.295148777311" Y="27.51056516295284" Z="-441.0000000000011" />
                <XVek X="-0.6199034944565297" Y="-0.3198912030411754" Z="0.716511881113951" />
                <YVek X="0.4952772868006389" Y="-0.867763124448906" Z="0.04108003196286716" />
                <ZVek X="0.6086214478146337" Y="0.3803377158047069" Z="0.6963642403200189" />
                <Rot X="0" Y="0" Z="0" />
                <Ext-Achswerte EA3="0" />
            </Frame>
        </Frames>
    </SNaht>
</FRAME-DUMP>
